osm_graph
