Metadata-Version: 1.1
Name: osm-graph
Version: 0.0.3
Summary: `osm-graph` is a package for NetworkX and OpenStreetMap.
Home-page: https://pypi.python.org/pypi/osm-graph
Author: Saito Tsutomu
Author-email: tsutomu.saito@beproud.jp
License: PSFL
Keywords: osm-graph
Platform: UNKNOWN
Classifier: Development Status :: 1 - Planning
Classifier: License :: OSI Approved :: Python Software Foundation License
Classifier: Programming Language :: Python
Classifier: Intended Audience :: Developers
Classifier: Intended Audience :: Science/Research
Classifier: Topic :: Scientific/Engineering
Classifier: Topic :: Software Development
